LICENSE
MANIFEST.in
README.rst
requirements.txt
setup.py
version.py
alignak_checks_graphite/__init__.py
alignak_checks_graphite.egg-info/PKG-INFO
alignak_checks_graphite.egg-info/SOURCES.txt
alignak_checks_graphite.egg-info/dependency_links.txt
alignak_checks_graphite.egg-info/not-zip-safe
alignak_checks_graphite.egg-info/requires.txt
alignak_checks_graphite.egg-info/top_level.txt
alignak_checks_graphite/etc/arbiter/packs/graphite/commands.cfg
alignak_checks_graphite/etc/arbiter/packs/graphite/groups.cfg
alignak_checks_graphite/etc/arbiter/packs/graphite/templates.cfg
alignak_checks_graphite/json/graphite/commands.json
alignak_checks_graphite/json/graphite/hostgroups.json
alignak_checks_graphite/json/graphite/hosts-templates.json
alignak_checks_graphite/json/graphite/servicegroups.json
alignak_checks_graphite/json/graphite/services-templates.json
alignak_checks_graphite/json/graphite/setup.sh